Metadata-Version: 2.1
Name: pyjaspar
Version: 3.0.0
Summary: A serverless interface to Biopython to access different versions of JASPAR database
Home-page: https://github.com/asntech/pyjaspar
Author: Aziz Khan
Author-email: azez.khan@gmail.com
License: GPL
Platform: linux/unix
Classifier: Intended Audience :: Developers
Classifier: Intended Audience :: Science/Research
Classifier: License :: OSI Approved :: MIT License
Classifier: Operating System :: OS Independent
Classifier: Programming Language :: Python
Classifier: Programming Language :: Python :: 3.6
Classifier: Programming Language :: Python :: 3.7
Classifier: Programming Language :: Python :: 3.8
Classifier: Topic :: Scientific/Engineering :: Bio-Informatics
Classifier: Topic :: Software Development :: Libraries :: Python Modules
